pyobs_tis/TIS.py
pyobs_tis/__init__.py
pyobs_tis/tiscamera.py
pyobs_tis-1.0.1.dist-info/METADATA
pyobs_tis-1.0.1.dist-info/WHEEL
pyobs_tis-1.0.1.dist-info/RECORD
