Metadata-Version: 2.1
Name: pyobs-tis
Version: 1.0.1
Summary: pyobs module for TIS cameras
License: MIT
Author: Tim-Oliver Husser
Author-email: thusser@uni-goettingen.de
Requires-Python: >=3.9,<3.13
Classifier: License :: OSI Approved :: MIT License
Classifier: Programming Language :: Python :: 3
Classifier: Programming Language :: Python :: 3.9
Classifier: Programming Language :: Python :: 3.10
Classifier: Programming Language :: Python :: 3.11
Classifier: Programming Language :: Python :: 3.12
